{
	"info": {
		"_postman_id": "25519dec-83de-4b57-8e14-a947a964849d",
		"name": "API Chaning",
		"schema": "https://schema.getpostman.com/json/collection/v2.1.0/collection.json",
		"_exporter_id": "28134428"
	},
	"item": [
		{
			"name": "Users List",
			"event": [
				{
					"listen": "test",
					"script": {
						"exec": [
							"jsonData=JSON.parse(responseBody);\r",
							"value = jsonData.data[1].employee_name;\r",
							"\r",
							"pm.collectionVariables.set(\"name\",value);"
						],
						"type": "text/javascript"
					}
				}
			],
			"request": {
				"method": "GET",
				"header": [],
				"url": {
					"raw": "https://dummy.restapiexample.com/api/v1/employees",
					"protocol": "https",
					"host": [
						"dummy",
						"restapiexample",
						"com"
					],
					"path": [
						"api",
						"v1",
						"employees"
					]
				}
			},
			"response": []
		},
		{
			"name": "Update user",
			"request": {
				"method": "PUT",
				"header": [],
				"body": {
					"mode": "raw",
					"raw": "{\r\n    \"name\":\"{{name}}\",\r\n    \"salary\":\"123\",\r\n    \"age\":\"23\"}",
					"options": {
						"raw": {
							"language": "json"
						}
					}
				},
				"url": {
					"raw": "https://dummy.restapiexample.com/api/v1/update/21",
					"protocol": "https",
					"host": [
						"dummy",
						"restapiexample",
						"com"
					],
					"path": [
						"api",
						"v1",
						"update",
						"21"
					]
				}
			},
			"response": []
		},
		{
			"name": "New Request",
			"request": {
				"method": "GET",
				"header": []
			},
			"response": []
		}
	],
	"event": [
		{
			"listen": "prerequest",
			"script": {
				"type": "text/javascript",
				"exec": [
					""
				]
			}
		},
		{
			"listen": "test",
			"script": {
				"type": "text/javascript",
				"exec": [
					""
				]
			}
		}
	],
	"variable": [
		{
			"key": "name",
			"value": "XYZ",
			"type": "string"
		}
	]
}